{
  "main": {
    "id": "8c3125cf79c48695",
    "type": "split",
    "children": [
      {
        "id": "8519a6d0425c0812",
        "type": "tabs",
        "children": [
          {
            "id": "38ab9ac921455131",
            "type": "leaf",
            "state": {
              "type": "markdown",
              "state": {
                "file": "Rifts/Locations/Charons_Crossing.md",
                "mode": "source",
                "source": false
              },
              "icon": "lucide-file",
              "title": "Charons_Crossing"
            }
          }
        ]
      }
    ],
    "direction": "vertical"
  },
  "left": {
    "id": "437f1664fdab4473",
    "type": "split",
    "children": [
      {
        "id": "049c54bb0a65c768",
        "type": "tabs",
        "children": [
          {
            "id": "7f8a53986d906d9f",
            "type": "leaf",
            "state": {
              "type": "file-explorer",
              "state": {
                "sortOrder": "alphabetical",
                "autoReveal": false
              },
              "icon": "lucide-folder-closed",
              "title": "Files"
            }
          },
          {
            "id": "46a05f8df31a767d",
            "type": "leaf",
            "state": {
              "type": "search",
              "state": {
                "query": "",
                "matchingCase": false,
                "explainSearch": false,
                "collapseAll": false,
                "extraContext": false,
                "sortOrder": "alphabetical"
              },
              "icon": "lucide-search",
              "title": "Search"
            }
          },
          {
            "id": "dacdea18969e463e",
            "type": "leaf",
            "state": {
              "type": "bookmarks",
              "state": {},
              "icon": "lucide-bookmark",
              "title": "Bookmarks"
            }
          }
        ]
      }
    ],
    "direction": "horizontal",
    "width": 300
  },
  "right": {
    "id": "17e88d75dbfe146f",
    "type": "split",
    "children": [
      {
        "id": "eb5e5f90b89d023a",
        "type": "tabs",
        "children": [
          {
            "id": "38261bb9f268f483",
            "type": "leaf",
            "state": {
              "type": "backlink",
              "state": {
                "collapseAll": false,
                "extraContext": false,
                "sortOrder": "alphabetical",
                "showSearch": false,
                "searchQuery": "",
                "backlinkCollapsed": false,
                "unlinkedCollapsed": true
              },
              "icon": "links-coming-in",
              "title": "Backlinks"
            }
          },
          {
            "id": "42594300f18907af",
            "type": "leaf",
            "state": {
              "type": "outgoing-link",
              "state": {
                "linksCollapsed": false,
                "unlinkedCollapsed": true
              },
              "icon": "links-going-out",
              "title": "Outgoing links"
            }
          },
          {
            "id": "af27d3cbf8448362",
            "type": "leaf",
            "state": {
              "type": "tag",
              "state": {
                "sortOrder": "frequency",
                "useHierarchy": true
              },
              "icon": "lucide-tags",
              "title": "Tags"
            }
          },
          {
            "id": "4910c11a4717b05d",
            "type": "leaf",
            "state": {
              "type": "outline",
              "state": {},
              "icon": "lucide-list",
              "title": "Outline"
            }
          }
        ]
      }
    ],
    "direction": "horizontal",
    "width": 300,
    "collapsed": true
  },
  "left-ribbon": {
    "hiddenItems": {
      "switcher:Open quick switcher": false,
      "graph:Open graph view": false,
      "canvas:Create new canvas": false,
      "daily-notes:Open today's daily note": false,
      "templates:Insert template": false,
      "command-palette:Open command palette": false
    }
  },
  "active": "38ab9ac921455131",
  "lastOpenFiles": [
    "Poetry/endlessly.md",
    "Untitled.md",
    "Rifts/Locations/Charons_Crossing.md",
    "Rifts/The_Cast.md",
    "example_processed.md",
    "README.md",
    "sample_markdown.md",
    "example.md",
    "Untitled",
    "Welcome.md"
  ]
}